_examples/__init__.py
datacode/__init__.py
datacode/hooks.py
datacode/load.py
datacode/logger.py
datacode/typing.py
datacode/compareids/__init__.py
datacode/compareids/backend.py
datacode/compareids/tools.py
datacode/compareids/frontends/__init__.py
datacode/compareids/frontends/text_summ.py
datacode/compareids/models/__init__.py
datacode/compareids/models/bars.py
datacode/compareids/models/base.py
datacode/compareids/models/datasets.py
datacode/compareids/models/flowchart.py
datacode/compareids/models/interface.py
datacode/compareids/models/main.py
datacode/compareids/models/steps.py
datacode/display/__init__.py
datacode/ff/__init__.py
datacode/ff/fftypes.py
datacode/ff/create/__init__.py
datacode/ff/create/average.py
datacode/ff/create/dualsort.py
datacode/ff/create/inputs.py
datacode/ff/create/label.py
datacode/ff/create/main.py
datacode/ff/create/mainport.py
datacode/ff/create/minus.py
datacode/ff/create/model.py
datacode/ff/create/reshape.py
datacode/ff/create/sort.py
datacode/formatters/__init__.py
datacode/formatters/stars.py
datacode/formatters/stderr.py
datacode/formatters/models/__init__.py
datacode/formatters/models/result.py
datacode/graph/__init__.py
datacode/graph/base.py
datacode/graph/edge.py
datacode/graph/node.py
datacode/graph/subgraph.py
datacode/models/__init__.py
datacode/models/analysis.py
datacode/models/dethash.py
datacode/models/explorer.py
datacode/models/index.py
datacode/models/last_modified.py
datacode/models/links.py
datacode/models/loader.py
datacode/models/options.py
datacode/models/outputter.py
datacode/models/source.py
datacode/models/symbols.py
datacode/models/types.py
datacode/models/column/__init__.py
datacode/models/column/column.py
datacode/models/column/index.py
datacode/models/dtypes/__init__.py
datacode/models/dtypes/base.py
datacode/models/dtypes/bit_size.py
datacode/models/dtypes/bool_type.py
datacode/models/dtypes/convert.py
datacode/models/dtypes/date_type.py
datacode/models/dtypes/datetime_type.py
datacode-0.20.8.dist-info/LICENSE.md
datacode-0.20.8.dist-info/METADATA
datacode-0.20.8.dist-info/WHEEL
datacode-0.20.8.dist-info/entry_points.txt
datacode-0.20.8.dist-info/top_level.txt
datacode-0.20.8.dist-info/RECORD
