Metadata-Version: 2.1
Name: datacode
Version: 0.20.8
Summary: High-level tools to analyze, summarize, and transform data
Home-page: https://github.com/nickderobertis/data-code
Author: Nick DeRobertis
Author-email: whoopnip@gmail.com
License: MIT
Project-URL: Code, https://github.com/nickderobertis/data-code
Project-URL: Documentation, https://nickderobertis.github.io/data-code
Platform: UNKNOWN
Classifier: Development Status :: 3 - Alpha
Classifier: Intended Audience :: Developers
Classifier: Programming Language :: Python :: 3.6
Classifier: Programming Language :: Python :: 3.7
Requires-Dist: pandas
Requires-Dist: pd-utils
Requires-Dist: matplotlib
Requires-Dist: regtools
Requires-Dist: pyexlatex
Requires-Dist: sympy
Requires-Dist: IPython
Requires-Dist: mixins
Requires-Dist: semopy (<2)
Requires-Dist: sklearn
Requires-Dist: typing-extensions
Requires-Dist: graphviz
Requires-Dist: deepdiff
